linux_ssh_mcp/__init__.py
linux_ssh_mcp/cli_v2.py
linux_ssh_mcp/config_manager.py
linux_ssh_mcp/config_validator.py
linux_ssh_mcp/mcp_server_v2.py
linux_ssh_mcp/scripting_engine.py
linux_ssh_mcp/simple_mcp_server.py
linux_ssh_mcp/simple_terminal_manager.py
linux_ssh_mcp/ssh_manager_v2.py
linux_ssh_mcp/terminal_emulator.py
linux_ssh_mcp/terminal_session_manager.py
linux_ssh_mcp-2.1.0.dist-info/METADATA
linux_ssh_mcp-2.1.0.dist-info/WHEEL
linux_ssh_mcp-2.1.0.dist-info/entry_points.txt
linux_ssh_mcp-2.1.0.dist-info/top_level.txt
linux_ssh_mcp-2.1.0.dist-info/RECORD
