Metadata-Version: 2.4
Name: linux-ssh-mcp
Version: 2.1.0
Summary: WindTerm-like terminal emulator with AI-powered configuration discovery and SSH management
Author: SSH MCP Development Team
Maintainer: SSH MCP Development Team
License-Expression: MIT
Project-URL: Homepage, https://github.com/sshmcp/linux-ssh-mcp
Project-URL: Documentation, https://github.com/sshmcp/linux-ssh-mcp/docs
Project-URL: Repository, https://github.com/sshmcp/linux-ssh-mcp
Project-URL: Bug Reports, https://github.com/sshmcp/linux-ssh-mcp/issues
Project-URL: Changelog, https://github.com/sshmcp/linux-ssh-mcp/CHANGELOG.md
Keywords: ssh,linux,mcp,terminal-emulator,windterm,server-management,automation,pty,async,devops,configuration-discovery,ai-assistant,server-automation,ssh-config,intelligent-management
Classifier: Development Status :: 5 - Production/Stable
Classifier: Intended Audience :: Developers
Classifier: Intended Audience :: System Administrators
Classifier: Operating System :: OS Independent
Classifier: Programming Language :: Python :: 3
Classifier: Programming Language :: Python :: 3.9
Classifier: Programming Language :: Python :: 3.10
Classifier: Programming Language :: Python :: 3.11
Classifier: Programming Language :: Python :: 3.12
Classifier: Programming Language :: Python :: 3.13
Classifier: Topic :: System :: Networking
Classifier: Topic :: System :: Systems Administration
Classifier: Topic :: Software Development :: Libraries :: Python Modules
Requires-Python: >=3.9
Requires-Dist: asyncssh>=2.17.0
Requires-Dist: aiofiles>=23.0.0
Requires-Dist: pydantic>=2.5.0
Requires-Dist: mcp>=1.0.0
Requires-Dist: cryptography>=41.0.0
Requires-Dist: python-dotenv>=1.0.0
Provides-Extra: dev
Requires-Dist: pytest>=7.4.0; extra == "dev"
Requires-Dist: pytest-asyncio>=0.21.0; extra == "dev"
Requires-Dist: pytest-cov>=4.1.0; extra == "dev"
Requires-Dist: pytest-mock>=3.12.0; extra == "dev"
Requires-Dist: black>=23.0.0; extra == "dev"
Requires-Dist: flake8>=6.0.0; extra == "dev"
Requires-Dist: mypy>=1.7.0; extra == "dev"
Provides-Extra: monitoring
Requires-Dist: prometheus-client>=0.19.0; extra == "monitoring"
Requires-Dist: grafana-api>=1.0.3; extra == "monitoring"
Provides-Extra: web
Requires-Dist: flask>=2.3.0; extra == "web"
Requires-Dist: flask-socketio>=5.3.0; extra == "web"
Requires-Dist: jinja2>=3.1.0; extra == "web"
Requires-Dist: bootstrap-flask>=2.2.0; extra == "web"
Provides-Extra: docker
Requires-Dist: docker>=6.1.0; extra == "docker"
Requires-Dist: docker-compose>=1.29.0; extra == "docker"
